{"chunk_definitions":[{"chunk_id":"csetup_chunk","chunk_label":"Setup","document_id":"CED20DBB","expansion_state":0,"options":{"engine":"r","label":"Setup"},"row":12,"row_count":1,"visible":true},{"chunk_id":"c82td4qpper6b","chunk_label":"Read GHI Order Line Detail Data","document_id":"CED20DBB","expansion_state":0,"options":{"engine":"r","label":"Read GHI Order Line Detail Data"},"row":33,"row_count":1,"visible":true},{"chunk_id":"cpz4zb3lf2w69","chunk_label":"Read GHI Revenue Data","document_id":"CED20DBB","expansion_state":0,"options":{"engine":"r","label":"Read GHI Revenue Data"},"row":52,"row_count":1,"visible":true},{"chunk_id":"cclrc7tskija4","chunk_label":"Read QDX Claim","document_id":"CED20DBB","expansion_state":0,"options":{"engine":"r","label":"Read QDX Claim, Payment & Case Data"},"row":63,"row_count":1,"visible":true},{"chunk_id":"cbytdi7c5pu9b","chunk_label":"unnamed-chunk-1","document_id":"582AD6A0","expansion_state":0,"options":{"engine":"r","label":"unnamed-chunk-10"},"row":83,"row_count":1,"visible":true},{"chunk_id":"c0ih8ehnm0coa","chunk_label":"Clean data","document_id":"CED20DBB","expansion_state":0,"options":{"engine":"r","label":"Clean data"},"row":113,"row_count":1,"visible":true},{"chunk_id":"czvc2hyjdglrp","chunk_label":"Summarize Revenue","document_id":"CED20DBB","expansion_state":0,"options":{"engine":"r","label":"Summarize Revenue"},"row":134,"row_count":1,"visible":true},{"chunk_id":"c8gd85o4curx1","chunk_label":"Summarize Claim","document_id":"CED20DBB","expansion_state":0,"options":{"engine":"r","label":"Summarize Claim"},"row":174,"row_count":1,"visible":true},{"chunk_id":"czyicxka122ax","chunk_label":"Summarize Payment & Adjustment","document_id":"CED20DBB","expansion_state":0,"options":{"engine":"r","label":"Summarize Payment & Adjustment"},"row":227,"row_count":1,"visible":true},{"chunk_id":"c830mfw2f4wii","chunk_label":"combine summarized data into Claim2Rev","document_id":"CED20DBB","expansion_state":0,"options":{"engine":"r","label":"combine summarized data into Claim2Rev"},"row":272,"row_count":1,"visible":true},{"chunk_id":"cxbsyol9t0m26","chunk_label":"TXN Detail","document_id":"CED20DBB","expansion_state":0,"options":{"engine":"r","label":"TXN Detail"},"row":310,"row_count":1,"visible":true},{"chunk_id":"cwetzl5o1fds7","chunk_label":"unnamed-chunk-2","document_id":"582AD6A0","expansion_state":0,"options":{"engine":"r","label":"unnamed-chunk-1"},"row":321,"row_count":1,"visible":true}],"doc_write_time":1519900040}